acqpack/__init__.py
acqpack/asicontroller.py
acqpack/autosampler.py
acqpack/fractioncollector.py
acqpack/gui.py
acqpack/manifold.py
acqpack/mfcs.py
acqpack/mfcs_64.dll
acqpack/motor.py
acqpack/utils.py
acqpack-1.1.1.dist-info/DESCRIPTION.rst
acqpack-1.1.1.dist-info/METADATA
acqpack-1.1.1.dist-info/RECORD
acqpack-1.1.1.dist-info/WHEEL
acqpack-1.1.1.dist-info/metadata.json
acqpack-1.1.1.dist-info/top_level.txt
