Metadata-Version: 2.0
Name: acqpack
Version: 1.1.1
Summary: Library for instrument control and automated data acquisition
Home-page: https://github.com/fordycelab/acqpack
Author: Scott Longwell
Author-email: longwell@stanford.edu
License: MIT license
Keywords: acqpack
Platform: UNKNOWN
Classifier: Development Status :: 2 - Pre-Alpha
Classifier: Intended Audience :: Developers
Classifier: License :: OSI Approved :: MIT License
Classifier: Natural Language :: English
Classifier: Programming Language :: Python :: 2
Classifier: Programming Language :: Python :: 2.7
Requires-Dist: PyYAML
Requires-Dist: ipywidgets (==6.0.0)
Requires-Dist: jupyter
Requires-Dist: matplotlib
Requires-Dist: numpy
Requires-Dist: opencv-contrib-python
Requires-Dist: opencv-python
Requires-Dist: pandas
Requires-Dist: pillow
Requires-Dist: pymodbus
Requires-Dist: pyserial
